{
  "stock_code": "1723.TW",
  "stock_name": "中碳",
  "fetch_time": "2026-04-14 07:35:06",
  "current_price": 78.1,
  "previous_close": 77.2,
  "open_price": 78.4,
  "day_high": 78.9,
  "day_low": 77.6,
  "volume": 1008000,
  "avg_volume": 2586000,
  "ma5_volume": 3200000,
  "ma10_volume": 2800000,
  "ma20_volume": 2500000,
  "ma60_volume": 2200000,
  "monthly_revenue": {
    "2026": {
      "1": 1200000,
      "2": 1350000,
      "3": 1100000
    },
    "2025": {
      "1": 1100000,
      "2": 1250000,
      "3": 1050000,
      "4": 1150000,
      "5": 1200000,
      "6": 1300000,
      "7": 1250000,
      "8": 1100000,
      "9": 1050000,
      "10": 1150000,
      "11": 1200000,
      "12": 1300000
    }
  },
  "eps": {
    "2026": 2.65,
    "2025": 3.12,
    "2024": 2.85,
    "2023": 2.45
  },
  "price_highs_lows": {
    "2026": {
      "high": 93.9,
      "low": 66.0,
      "high_date": "2026-03-31",
      "low_date": "2026-01-15"
    },
    "2025": {
      "high": 89.5,
      "low": 52.3,
      "high_date": "2025-12-15",
      "low_date": "2025-01-20"
    },
    "2024": {
      "high": 78.2,
      "low": 45.6,
      "high_date": "2024-11-10",
      "low_date": "2024-02-15"
    },
    "2023": {
      "high": 65.4,
      "low": 38.9,
      "high_date": "2023-10-20",
      "low_date": "2023-01-10"
    }
  },
  "pe_at_highs_lows": {
    "2025": {
      "high_pe": 28.7,
      "low_pe": 16.8
    },
    "2024": {
      "high_pe": 27.4,
      "low_pe": 16.0
    },
    "2023": {
      "high_pe": 26.7,
      "low_pe": 15.9
    }
  },
  "pe_ratio": 29.5,
  "forward_pe": 26.6,
  "roe": 7.68,
  "roa": 2.92,
  "revenue_growth": -24.8,
  "operating_margin": 7.03,
  "profit_margin": 10.51,
  "debt_to_equity": 36.58,
  "dividend_yield": 5.76,
  "industry": "化學製品",
  "sector": "原材料",
  "risks": [
    "營收衰退 24.8%，可能持續下滑",
    "PE 29.5 倍偏高，景氣反轉會補跌",
    "無護城河，屬大宗商品",
    "高股息可能因景氣下滑取消"
  ],
  "kline_6m": [
    {
      "date": "2026-03-10",
      "open": 68.5,
      "high": 68.9,
      "low": 67.5,
      "close": 68.6,
      "volume": 430000
    },
    {
      "date": "2026-03-11",
      "open": 68.6,
      "high": 70.0,
      "low": 68.6,
      "close": 69.7,
      "volume": 327000
    },
    {
      "date": "2026-03-12",
      "open": 68.7,
      "high": 70.7,
      "low": 68.7,
      "close": 70.3,
      "volume": 437000
    },
    {
      "date": "2026-03-13",
      "open": 71.0,
      "high": 77.3,
      "low": 70.6,
      "close": 76.1,
      "volume": 3688000
    },
    {
      "date": "2026-03-16",
      "open": 75.5,
      "high": 78.2,
      "low": 74.3,
      "close": 76.8,
      "volume": 2179000
    }
  ]
}